odoo/addons/l10n_it_account_stamp/README.rst
odoo/addons/l10n_it_account_stamp/__init__.py
odoo/addons/l10n_it_account_stamp/__manifest__.py
odoo/addons/l10n_it_account_stamp/data/data.xml
odoo/addons/l10n_it_account_stamp/i18n/it.po
odoo/addons/l10n_it_account_stamp/i18n/l10n_it_account_stamp.pot
odoo/addons/l10n_it_account_stamp/models/__init__.py
odoo/addons/l10n_it_account_stamp/models/company.py
odoo/addons/l10n_it_account_stamp/models/invoice.py
odoo/addons/l10n_it_account_stamp/models/product.py
odoo/addons/l10n_it_account_stamp/readme/CONFIGURE.rst
odoo/addons/l10n_it_account_stamp/readme/CONTRIBUTORS.rst
odoo/addons/l10n_it_account_stamp/readme/DESCRIPTION.rst
odoo/addons/l10n_it_account_stamp/readme/USAGE.rst
odoo/addons/l10n_it_account_stamp/static/description/icon.png
odoo/addons/l10n_it_account_stamp/static/description/index.html
odoo/addons/l10n_it_account_stamp/tests/__init__.py
odoo/addons/l10n_it_account_stamp/tests/test_account_stamp.py
odoo/addons/l10n_it_account_stamp/views/account_invoice_report.xml
odoo/addons/l10n_it_account_stamp/views/company_view.xml
odoo/addons/l10n_it_account_stamp/views/invoice_view.xml
odoo/addons/l10n_it_account_stamp/views/product_view.xml
odoo12_addon_l10n_it_account_stamp-12.0.1.4.0.dist-info/METADATA
odoo12_addon_l10n_it_account_stamp-12.0.1.4.0.dist-info/WHEEL
odoo12_addon_l10n_it_account_stamp-12.0.1.4.0.dist-info/top_level.txt
odoo12_addon_l10n_it_account_stamp-12.0.1.4.0.dist-info/RECORD
