Metadata-Version: 2.1
Name: odoo12-addon-l10n-it-account-stamp
Version: 12.0.1.4.0
Summary: Gestione automatica dell'imposta di bollo
Home-page: https://github.com/OCA/l10n-italy
Author: Ermanno Gnan, Sergio Corato, Enrico Ganzaroli, Odoo Community Association (OCA)
Author-email: support@odoo-community.org
License: LGPL-3
Platform: UNKNOWN
Classifier: Programming Language :: Python
Classifier: Framework :: Odoo
Classifier: Framework :: Odoo :: 12.0
Classifier: License :: OSI Approved :: GNU Lesser General Public License v3 (LGPLv3)
Requires-Python: >=3.5
Requires-Dist: odoo (<12.1dev,>=12.0a)
